README.md
setup.cfg
setup.py
platron/__init__.py
platron/sdk_exception.py
platron/sig_helper.py
platron.egg-info/PKG-INFO
platron.egg-info/SOURCES.txt
platron.egg-info/dependency_links.txt
platron.egg-info/requires.txt
platron.egg-info/top_level.txt
platron/callback/__init__.py
platron/callback/callback.py
platron/request/clients/__init__.py
platron/request/clients/platron_client.py
platron/request/clients/post_client.py
platron/request/data_objects/__init__.py
platron/request/data_objects/avia_gds.py
platron/request/data_objects/bank_card.py
platron/request/data_objects/data_object.py
platron/request/data_objects/item.py
platron/request/data_objects/long_record.py
platron/request/data_objects/tripleg.py
platron/request/request_builders/__init__.py
platron/request/request_builders/cancel_builder.py
platron/request/request_builders/create_moneyback_builder.py
platron/request/request_builders/create_refund_request_builder.py
platron/request/request_builders/do_capture_builder.py
platron/request/request_builders/get_bin_info_builder.py
platron/request/request_builders/get_moneyback_status_builder.py
platron/request/request_builders/get_receipt_status_builder.py
platron/request/request_builders/get_registry_builder.py
platron/request/request_builders/get_status_builder.py
platron/request/request_builders/init_payment_builder.py
platron/request/request_builders/make_recurring_builder.py
platron/request/request_builders/moneyback_system_list_builder.py
platron/request/request_builders/ps_list_builder.py
platron/request/request_builders/receipt_builder.py
platron/request/request_builders/recurring_clear_schedule_builder.py
platron/request/request_builders/recurring_get_schedule_builder.py
platron/request/request_builders/recurring_set_schedule_buider.py
platron/request/request_builders/request_builder.py
platron/request/request_builders/revoke_builder.py
tests/integration/__init__.py
tests/integration/base_integration_test.py
tests/integration/cancel_test.py
tests/integration/create_transaction_test.py
tests/integration/get_registry_test.py
tests/integration/get_status_test.py
tests/integration/merchant_settings_sample.py
