Metadata-Version: 1.0
Name: platron
Version: 3.1.0
Summary: A client library for the Platron API
Home-page: https://github.com/Platron/python-sdk
Author: Platron
Author-email: it@platron.ru
License: UNKNOWN
Keywords: platron payment api
Platform: UNKNOWN
